rnnbuilder/__init__.py
rnnbuilder/base/__init__.py
rnnbuilder/base/_modules.py
rnnbuilder/base/_utils.py
rnnbuilder/custom/__init__.py
rnnbuilder/custom/_factories.py
rnnbuilder/custom/_modules.py
rnnbuilder/nn/__init__.py
rnnbuilder/rnn/__init__.py
rnnbuilder/rnn/_modules.py
rnnbuilder/snn/__init__.py
rnnbuilder/snn/_modules.py
rnnbuilder-0.1.1.dist-info/LICENSE
rnnbuilder-0.1.1.dist-info/METADATA
rnnbuilder-0.1.1.dist-info/WHEEL
rnnbuilder-0.1.1.dist-info/top_level.txt
rnnbuilder-0.1.1.dist-info/RECORD
